fountain
setup.cfg
setup.py
Agora_Fountain.egg-info/PKG-INFO
Agora_Fountain.egg-info/SOURCES.txt
Agora_Fountain.egg-info/dependency_links.txt
Agora_Fountain.egg-info/namespace_packages.txt
Agora_Fountain.egg-info/requires.txt
Agora_Fountain.egg-info/top_level.txt
agora/__init__.py
agora/fountain/__init__.py
agora/fountain/api.py
agora/fountain/exceptions.py
agora/fountain/metadata.json
agora/fountain/index/__init__.py
agora/fountain/index/core.py
agora/fountain/index/paths.py
agora/fountain/index/seeds.py
agora/fountain/server/__init__.py
agora/fountain/server/config.py
agora/fountain/server/static/LoveYaLikeASister.eot
agora/fountain/server/static/LoveYaLikeASister.svg
agora/fountain/server/static/LoveYaLikeASister.ttf
agora/fountain/server/static/LoveYaLikeASister.woff
agora/fountain/server/static/Monoxil.otf
agora/fountain/server/static/eager.eot
agora/fountain/server/static/eager.svg
agora/fountain/server/static/eager.ttf
agora/fountain/server/static/eager.woff
agora/fountain/server/static/graph-path.js
agora/fountain/server/static/graph-vocabs.js
agora/fountain/server/static/logo-agora.png
agora/fountain/server/static/logo-sdh.png
agora/fountain/server/static/paper.jpg
agora/fountain/server/static/style.css
agora/fountain/server/templates/graph-path.html
agora/fountain/server/templates/graph-vocabs.html
agora/fountain/tests/__init__.py
agora/fountain/tests/generic_paths_test.py
agora/fountain/tests/seed_test.py
agora/fountain/tests/simple_two_concepts_test.py
agora/fountain/tests/vocab_test.py
agora/fountain/tests/cycles/__init__.py
agora/fountain/tests/cycles/self_and_simple_concept_cycle_test.py
agora/fountain/tests/cycles/self_and_two_concept_cycle_test.py
agora/fountain/tests/cycles/self_cycle_test.py
agora/fountain/tests/cycles/three_concept_cycle_test.py
agora/fountain/tests/cycles/two_concept_cycle_test.py
agora/fountain/tests/cycles/two_self_cycles_test.py
agora/fountain/tests/cycles/complex/__init__.py
agora/fountain/tests/cycles/complex/two_in_three_concept_cycle_test.py
agora/fountain/tests/polymorph/__init__.py
agora/fountain/tests/polymorph/one_subclass_test.py
agora/fountain/tests/polymorph/self_cycle_and_subclass_test.py
