Metadata-Version: 1.1
Name: Agora-Fountain
Version: 0.5.5
Summary: The Agora core service for ontology paths discovery and seeds management
Home-page: https://github.com/smartdeveloperhub/agora-fountain
Author: Fernando Serena
Author-email: fernando.serena@centeropenmiddleware.com
License: Apache 2
Download-URL: https://github.com/smartdeveloperhub/agora-fountain/tarball/0.5.1-alpha1
Keywords: linked-data,ontology,path
Platform: UNKNOWN
